[
  {
    "type": "constructor",
    "inputs": [
      {
        "name": "_dao",
        "type": "address",
        "internalType": "address"
      },
      {
        "name": "_ledger",
        "type": "address",
        "internalType": "address"
      },
      {
        "name": "_hub",
        "type": "address",
        "internalType": "address"
      }
    ],
    "stateMutability": "nonpayable"
  },
  {
    "type": "function",
    "name": "MAX_SCORE",
    "inputs": [],
    "outputs": [
      {
        "name": "",
        "type": "uint16",
        "internalType": "uint16"
      }
    ],
    "stateMutability": "view"
  },
  {
    "type": "function",
    "name": "MIN_SCORE",
    "inputs": [],
    "outputs": [
      {
        "name": "",
        "type": "uint16",
        "internalType": "uint16"
      }
    ],
    "stateMutability": "view"
  },
  {
    "type": "function",
    "name": "NEUTRAL",
    "inputs": [],
    "outputs": [
      {
        "name": "",
        "type": "uint16",
        "internalType": "uint16"
      }
    ],
    "stateMutability": "view"
  },
  {
    "type": "function",
    "name": "addScoreSource",
    "inputs": [
      {
        "name": "source",
        "type": "address",
        "internalType": "address"
      },
      {
        "name": "name",
        "type": "string",
        "internalType": "string"
      },
      {
        "name": "weight",
        "type": "uint8",
        "internalType": "uint8"
      }
    ],
    "outputs": [],
    "stateMutability": "nonpayable"
  },
  {
    "type": "function",
    "name": "badgeExpiry",
    "inputs": [
      {
        "name": "",
        "type": "address",
        "internalType": "address"
      },
      {
        "name": "",
        "type": "bytes32",
        "internalType": "bytes32"
      }
    ],
    "outputs": [
      {
        "name": "",
        "type": "uint256",
        "internalType": "uint256"
      }
    ],
    "stateMutability": "view"
  },
  {
    "type": "function",
    "name": "calculateAutomatedScore",
    "inputs": [
      {
        "name": "subject",
        "type": "address",
        "internalType": "address"
      }
    ],
    "outputs": [
      {
        "name": "",
        "type": "uint16",
        "internalType": "uint16"
      }
    ],
    "stateMutability": "view"
  },
  {
    "type": "function",
    "name": "calculateOnChainScore",
    "inputs": [
      {
        "name": "subject",
        "type": "address",
        "internalType": "address"
      }
    ],
    "outputs": [
      {
        "name": "",
        "type": "uint16",
        "internalType": "uint16"
      }
    ],
    "stateMutability": "view"
  },
  {
    "type": "function",
    "name": "dao",
    "inputs": [],
    "outputs": [
      {
        "name": "",
        "type": "address",
        "internalType": "address"
      }
    ],
    "stateMutability": "view"
  },
  {
    "type": "function",
    "name": "daoScoreWeight",
    "inputs": [],
    "outputs": [
      {
        "name": "",
        "type": "uint8",
        "internalType": "uint8"
      }
    ],
    "stateMutability": "view"
  },
  {
    "type": "function",
    "name": "getScore",
    "inputs": [
      {
        "name": "subject",
        "type": "address",
        "internalType": "address"
      }
    ],
    "outputs": [
      {
        "name": "",
        "type": "uint16",
        "internalType": "uint16"
      }
    ],
    "stateMutability": "view"
  },
  {
    "type": "function",
    "name": "getScoreSourceCount",
    "inputs": [],
    "outputs": [
      {
        "name": "total",
        "type": "uint256",
        "internalType": "uint256"
      },
      {
        "name": "active",
        "type": "uint256",
        "internalType": "uint256"
      }
    ],
    "stateMutability": "view"
  },
  {
    "type": "function",
    "name": "hasBadge",
    "inputs": [
      {
        "name": "",
        "type": "address",
        "internalType": "address"
      },
      {
        "name": "",
        "type": "bytes32",
        "internalType": "bytes32"
      }
    ],
    "outputs": [
      {
        "name": "",
        "type": "bool",
        "internalType": "bool"
      }
    ],
    "stateMutability": "view"
  },
  {
    "type": "function",
    "name": "highTrustThreshold",
    "inputs": [],
    "outputs": [
      {
        "name": "",
        "type": "uint16",
        "internalType": "uint16"
      }
    ],
    "stateMutability": "view"
  },
  {
    "type": "function",
    "name": "isBadgeValid",
    "inputs": [
      {
        "name": "subject",
        "type": "address",
        "internalType": "address"
      },
      {
        "name": "badge",
        "type": "bytes32",
        "internalType": "bytes32"
      }
    ],
    "outputs": [
      {
        "name": "",
        "type": "bool",
        "internalType": "bool"
      }
    ],
    "stateMutability": "view"
  },
  {
    "type": "function",
    "name": "ledger",
    "inputs": [],
    "outputs": [
      {
        "name": "",
        "type": "address",
        "internalType": "contract ProofLedger"
      }
    ],
    "stateMutability": "view"
  },
  {
    "type": "function",
    "name": "lowTrustThreshold",
    "inputs": [],
    "outputs": [
      {
        "name": "",
        "type": "uint16",
        "internalType": "uint16"
      }
    ],
    "stateMutability": "view"
  },
  {
    "type": "function",
    "name": "minForGovernance",
    "inputs": [],
    "outputs": [
      {
        "name": "",
        "type": "uint16",
        "internalType": "uint16"
      }
    ],
    "stateMutability": "view"
  },
  {
    "type": "function",
    "name": "minForMerchant",
    "inputs": [],
    "outputs": [
      {
        "name": "",
        "type": "uint16",
        "internalType": "uint16"
      }
    ],
    "stateMutability": "view"
  },
  {
    "type": "function",
    "name": "onChainScoreWeight",
    "inputs": [],
    "outputs": [
      {
        "name": "",
        "type": "uint8",
        "internalType": "uint8"
      }
    ],
    "stateMutability": "view"
  },
  {
    "type": "function",
    "name": "punish",
    "inputs": [
      {
        "name": "subject",
        "type": "address",
        "internalType": "address"
      },
      {
        "name": "delta",
        "type": "uint16",
        "internalType": "uint16"
      },
      {
        "name": "reason",
        "type": "string",
        "internalType": "string"
      }
    ],
    "outputs": [],
    "stateMutability": "nonpayable"
  },
  {
    "type": "function",
    "name": "removeScoreSource",
    "inputs": [
      {
        "name": "source",
        "type": "address",
        "internalType": "address"
      }
    ],
    "outputs": [],
    "stateMutability": "nonpayable"
  },
  {
    "type": "function",
    "name": "reward",
    "inputs": [
      {
        "name": "subject",
        "type": "address",
        "internalType": "address"
      },
      {
        "name": "delta",
        "type": "uint16",
        "internalType": "uint16"
      },
      {
        "name": "reason",
        "type": "string",
        "internalType": "string"
      }
    ],
    "outputs": [],
    "stateMutability": "nonpayable"
  },
  {
    "type": "function",
    "name": "scoreSourceIndex",
    "inputs": [
      {
        "name": "",
        "type": "address",
        "internalType": "address"
      }
    ],
    "outputs": [
      {
        "name": "",
        "type": "uint256",
        "internalType": "uint256"
      }
    ],
    "stateMutability": "view"
  },
  {
    "type": "function",
    "name": "scoreSources",
    "inputs": [
      {
        "name": "",
        "type": "uint256",
        "internalType": "uint256"
      }
    ],
    "outputs": [
      {
        "name": "source",
        "type": "address",
        "internalType": "address"
      },
      {
        "name": "name",
        "type": "string",
        "internalType": "string"
      },
      {
        "name": "weight",
        "type": "uint8",
        "internalType": "uint8"
      },
      {
        "name": "active",
        "type": "bool",
        "internalType": "bool"
      }
    ],
    "stateMutability": "view"
  },
  {
    "type": "function",
    "name": "setBadge",
    "inputs": [
      {
        "name": "subject",
        "type": "address",
        "internalType": "address"
      },
      {
        "name": "badge",
        "type": "bytes32",
        "internalType": "bytes32"
      },
      {
        "name": "active",
        "type": "bool",
        "internalType": "bool"
      },
      {
        "name": "expiry",
        "type": "uint256",
        "internalType": "uint256"
      }
    ],
    "outputs": [],
    "stateMutability": "nonpayable"
  },
  {
    "type": "function",
    "name": "setBadgeBatch",
    "inputs": [
      {
        "name": "subjects",
        "type": "address[]",
        "internalType": "address[]"
      },
      {
        "name": "badge",
        "type": "bytes32",
        "internalType": "bytes32"
      },
      {
        "name": "active",
        "type": "bool",
        "internalType": "bool"
      },
      {
        "name": "expiry",
        "type": "uint256",
        "internalType": "uint256"
      }
    ],
    "outputs": [],
    "stateMutability": "nonpayable"
  },
  {
    "type": "function",
    "name": "setDecentralizationWeights",
    "inputs": [
      {
        "name": "daoWeight",
        "type": "uint8",
        "internalType": "uint8"
      },
      {
        "name": "onChainWeight",
        "type": "uint8",
        "internalType": "uint8"
      }
    ],
    "outputs": [],
    "stateMutability": "nonpayable"
  },
  {
    "type": "function",
    "name": "setModules",
    "inputs": [
      {
        "name": "_ledger",
        "type": "address",
        "internalType": "address"
      },
      {
        "name": "_hub",
        "type": "address",
        "internalType": "address"
      }
    ],
    "outputs": [],
    "stateMutability": "nonpayable"
  },
  {
    "type": "function",
    "name": "setScore",
    "inputs": [
      {
        "name": "subject",
        "type": "address",
        "internalType": "address"
      },
      {
        "name": "newScore",
        "type": "uint16",
        "internalType": "uint16"
      },
      {
        "name": "reason",
        "type": "string",
        "internalType": "string"
      }
    ],
    "outputs": [],
    "stateMutability": "nonpayable"
  },
  {
    "type": "function",
    "name": "setThresholds",
    "inputs": [
      {
        "name": "low",
        "type": "uint16",
        "internalType": "uint16"
      },
      {
        "name": "high",
        "type": "uint16",
        "internalType": "uint16"
      },
      {
        "name": "minGov",
        "type": "uint16",
        "internalType": "uint16"
      },
      {
        "name": "minMerch",
        "type": "uint16",
        "internalType": "uint16"
      }
    ],
    "outputs": [],
    "stateMutability": "nonpayable"
  },
  {
    "type": "function",
    "name": "vaultHub",
    "inputs": [],
    "outputs": [
      {
        "name": "",
        "type": "address",
        "internalType": "contract IVaultHub_Trust"
      }
    ],
    "stateMutability": "view"
  },
  {
    "type": "event",
    "name": "DecentralizationUpdated",
    "inputs": [
      {
        "name": "daoWeight",
        "type": "uint8",
        "indexed": false,
        "internalType": "uint8"
      },
      {
        "name": "onChainWeight",
        "type": "uint8",
        "indexed": false,
        "internalType": "uint8"
      }
    ],
    "anonymous": false
  },
  {
    "type": "event",
    "name": "HubSet",
    "inputs": [
      {
        "name": "vaultHub",
        "type": "address",
        "indexed": false,
        "internalType": "address"
      }
    ],
    "anonymous": false
  },
  {
    "type": "event",
    "name": "LedgerSet",
    "inputs": [
      {
        "name": "ledger",
        "type": "address",
        "indexed": false,
        "internalType": "address"
      }
    ],
    "anonymous": false
  },
  {
    "type": "event",
    "name": "ScoreSet",
    "inputs": [
      {
        "name": "subject",
        "type": "address",
        "indexed": true,
        "internalType": "address"
      },
      {
        "name": "oldScore",
        "type": "uint16",
        "indexed": false,
        "internalType": "uint16"
      },
      {
        "name": "newScore",
        "type": "uint16",
        "indexed": false,
        "internalType": "uint16"
      },
      {
        "name": "reason",
        "type": "string",
        "indexed": false,
        "internalType": "string"
      }
    ],
    "anonymous": false
  },
  {
    "type": "event",
    "name": "ScoreSourceAdded",
    "inputs": [
      {
        "name": "source",
        "type": "address",
        "indexed": true,
        "internalType": "address"
      },
      {
        "name": "name",
        "type": "string",
        "indexed": false,
        "internalType": "string"
      },
      {
        "name": "weight",
        "type": "uint8",
        "indexed": false,
        "internalType": "uint8"
      }
    ],
    "anonymous": false
  },
  {
    "type": "event",
    "name": "ScoreSourceRemoved",
    "inputs": [
      {
        "name": "source",
        "type": "address",
        "indexed": true,
        "internalType": "address"
      }
    ],
    "anonymous": false
  },
  {
    "type": "event",
    "name": "ThresholdsSet",
    "inputs": [
      {
        "name": "low",
        "type": "uint16",
        "indexed": false,
        "internalType": "uint16"
      },
      {
        "name": "high",
        "type": "uint16",
        "indexed": false,
        "internalType": "uint16"
      },
      {
        "name": "minForGov",
        "type": "uint16",
        "indexed": false,
        "internalType": "uint16"
      },
      {
        "name": "minForMerchant",
        "type": "uint16",
        "indexed": false,
        "internalType": "uint16"
      }
    ],
    "anonymous": false
  },
  {
    "type": "error",
    "name": "TRUST_Bounds",
    "inputs": []
  },
  {
    "type": "error",
    "name": "TRUST_NotDAO",
    "inputs": []
  },
  {
    "type": "error",
    "name": "TRUST_Zero",
    "inputs": []
  }
]
