{
  "compilerOptions": {
    "target": "ES2020",
    "lib": [
      "ES2020",
      "DOM",
      "DOM.Iterable"
    ],
    "jsx": "react-jsx",
    "module": "ESNext",
    "moduleResolution": "bundler",
    "resolveJsonModule": true,
    "allowJs": false,
    "strict": true,
    "noUncheckedIndexedAccess": true,
    "noImplicitReturns": true,
    "noFallthroughCasesInSwitch": true,
    "noEmit": true,
    "esModuleInterop": true,
    "skipLibCheck": true,
    "forceConsistentCasingInFileNames": true,
    "incremental": false,
    "isolatedModules": true,
    "plugins": [
      {
        "name": "next"
      }
    ],
    "paths": {
      "@/*": [
        "./*"
      ]
    },
    "baseUrl": "/workspaces/Vfide",
    "ignoreDeprecations": "6.0",
    "tsBuildInfoFile": "/workspaces/Vfide/.typecheck-temp/shard-2tB1t0/app-01.tsbuildinfo"
  },
  "include": [
    "/workspaces/Vfide/next-env.d.ts",
    "/workspaces/Vfide/jest.d.ts",
    "/workspaces/Vfide/next.config.ts",
    "/workspaces/Vfide/proxy.ts",
    "/workspaces/Vfide/instrumentation.ts",
    "/workspaces/Vfide/instrumentation-client.ts",
    "/workspaces/Vfide/sentry.edge.config.ts",
    "/workspaces/Vfide/sentry.server.config.ts",
    "/workspaces/Vfide/.next/types/**/*.ts",
    "/workspaces/Vfide/data/**/*.ts",
    "/workspaces/Vfide/data/**/*.tsx",
    "/workspaces/Vfide/hooks/**/*.ts",
    "/workspaces/Vfide/hooks/**/*.tsx",
    "/workspaces/Vfide/providers/**/*.ts",
    "/workspaces/Vfide/providers/**/*.tsx",
    "/workspaces/Vfide/public/**/*.ts",
    "/workspaces/Vfide/public/**/*.tsx",
    "/workspaces/Vfide/types/**/*.d.ts",
    "/workspaces/Vfide/types/**/*.ts",
    "/workspaces/Vfide/types/**/*.tsx",
    "/workspaces/Vfide/app/components/**/*.ts",
    "/workspaces/Vfide/app/components/**/*.tsx",
    "/workspaces/Vfide/app/(auth)/**/*.ts",
    "/workspaces/Vfide/app/(auth)/**/*.tsx",
    "/workspaces/Vfide/app/(auth)/**/*.d.ts",
    "/workspaces/Vfide/app/(commerce)/**/*.ts",
    "/workspaces/Vfide/app/(commerce)/**/*.tsx",
    "/workspaces/Vfide/app/(commerce)/**/*.d.ts",
    "/workspaces/Vfide/app/(finance)/**/*.ts",
    "/workspaces/Vfide/app/(finance)/**/*.tsx",
    "/workspaces/Vfide/app/(finance)/**/*.d.ts",
    "/workspaces/Vfide/app/(gamification)/**/*.ts",
    "/workspaces/Vfide/app/(gamification)/**/*.tsx",
    "/workspaces/Vfide/app/(gamification)/**/*.d.ts",
    "/workspaces/Vfide/app/(governance)/**/*.ts",
    "/workspaces/Vfide/app/(governance)/**/*.tsx",
    "/workspaces/Vfide/app/(governance)/**/*.d.ts",
    "/workspaces/Vfide/app/(marketing)/**/*.ts",
    "/workspaces/Vfide/app/(marketing)/**/*.tsx",
    "/workspaces/Vfide/app/(marketing)/**/*.d.ts",
    "/workspaces/Vfide/app/(security)/**/*.ts",
    "/workspaces/Vfide/app/(security)/**/*.tsx",
    "/workspaces/Vfide/app/(security)/**/*.d.ts",
    "/workspaces/Vfide/app/(seer)/**/*.ts",
    "/workspaces/Vfide/app/(seer)/**/*.tsx",
    "/workspaces/Vfide/app/(seer)/**/*.d.ts",
    "/workspaces/Vfide/app/(social)/**/*.ts",
    "/workspaces/Vfide/app/(social)/**/*.tsx",
    "/workspaces/Vfide/app/(social)/**/*.d.ts",
    "/workspaces/Vfide/app/about/**/*.ts",
    "/workspaces/Vfide/app/about/**/*.tsx",
    "/workspaces/Vfide/app/about/**/*.d.ts",
    "/workspaces/Vfide/app/achievements/**/*.ts",
    "/workspaces/Vfide/app/achievements/**/*.tsx",
    "/workspaces/Vfide/app/achievements/**/*.d.ts",
    "/workspaces/Vfide/app/admin/**/*.ts",
    "/workspaces/Vfide/app/admin/**/*.tsx",
    "/workspaces/Vfide/app/admin/**/*.d.ts",
    "/workspaces/Vfide/app/error.tsx",
    "/workspaces/Vfide/app/global-error.tsx",
    "/workspaces/Vfide/app/layout.tsx",
    "/workspaces/Vfide/app/loading.tsx",
    "/workspaces/Vfide/app/not-found.tsx",
    "/workspaces/Vfide/app/page.tsx",
    "/workspaces/Vfide/app/robots.ts",
    "/workspaces/Vfide/app/sitemap.ts"
  ],
  "exclude": [
    "/workspaces/Vfide/node_modules",
    "/workspaces/Vfide/artifacts/**",
    "/workspaces/Vfide/scripts/**",
    "/workspaces/Vfide/migrations/**",
    "/workspaces/Vfide/test/**",
    "/workspaces/Vfide/websocket-server/**",
    "/workspaces/Vfide/**/*.test.ts",
    "/workspaces/Vfide/**/*.test.tsx",
    "/workspaces/Vfide/**/*.spec.ts",
    "/workspaces/Vfide/**/*.spec.tsx",
    "/workspaces/Vfide/**/*.stories.ts",
    "/workspaces/Vfide/**/*.stories.tsx",
    "/workspaces/Vfide/**/*.stories.mdx",
    "/workspaces/Vfide/config/**",
    "/workspaces/Vfide/contracts/**",
    "/workspaces/Vfide/hardhat.config.ts",
    "/workspaces/Vfide/hardhat.unlimited.config.ts",
    "/workspaces/Vfide/playwright.config.ts",
    "/workspaces/Vfide/playwright.config.runtime.ts",
    "/workspaces/Vfide/playwright/**",
    "/workspaces/Vfide/vitest.config.ts",
    "/workspaces/Vfide/vitest.setup.ts",
    "/workspaces/Vfide/__tests__/**",
    "/workspaces/Vfide/extracted-archives/**"
  ]
}
